cloudinsight_extractor/__init__.py
cloudinsight_extractor/main.py
cloudinsight_extractor/prompts.py
cloudinsight_extractor-2025.12.21112353.dist-info/METADATA
cloudinsight_extractor-2025.12.21112353.dist-info/WHEEL
cloudinsight_extractor-2025.12.21112353.dist-info/top_level.txt
cloudinsight_extractor-2025.12.21112353.dist-info/RECORD
