Metadata-Version: 2.4
Name: cloudinsight-extractor
Version: 2025.12.21112353
Summary: A new package designed to analyze and extract structured insights from user-submitted summaries or descriptions related to cloud infrastructure topics. Given an input text about a specific subject lik
Author-email: cloudinsight-extractor <hi@eugene.plus>
License: MIT
Project-URL: Homepage, https://github.com/chigwell/cloudinsight-extractor
Requires-Python: >=3.9
Requires-Dist: langchain-llm7>=0.0.0
Requires-Dist: llmatch-messages>=0.0.0
Requires-Dist: langchain-core>=0.3.0
